edgepi_rpc_client/__init__.py
edgepi_rpc_client/client_rpc_channel.py
edgepi_rpc_client/error/__init__.py
edgepi_rpc_client/error/rpc_failure.py
edgepi_rpc_client/services/__init__.py
edgepi_rpc_client/services/adc/__init__.py
edgepi_rpc_client/services/adc/adc_pb_enums.py
edgepi_rpc_client/services/adc/client_adc_service.py
edgepi_rpc_client/services/dac/__init__.py
edgepi_rpc_client/services/dac/client_dac_service.py
edgepi_rpc_client/services/dac/dac_pb_enums.py
edgepi_rpc_client/services/din/__init__.py
edgepi_rpc_client/services/din/client_din_service.py
edgepi_rpc_client/services/din/din_pb_enums.py
edgepi_rpc_client/services/dout/__init__.py
edgepi_rpc_client/services/dout/client_dout_service.py
edgepi_rpc_client/services/dout/dout_pb_enums.py
edgepi_rpc_client/services/led/__init__.py
edgepi_rpc_client/services/led/client_led_service.py
edgepi_rpc_client/services/led/led_pb_enums.py
edgepi_rpc_client/services/pwm/__init__.py
edgepi_rpc_client/services/pwm/client_pwm_service.py
edgepi_rpc_client/services/pwm/pwm_pb_enums.py
edgepi_rpc_client/services/relay/__init__.py
edgepi_rpc_client/services/relay/client_relay_service.py
edgepi_rpc_client/services/tc/__init__.py
edgepi_rpc_client/services/tc/client_tc_service.py
edgepi_rpc_client/services/tc/tc_pb_enums.py
edgepi_rpc_client/util/__init__.py
edgepi_rpc_client/util/helpers.py
tests/__init__.py
tests/integration/__init__.py
tests/integration/test_adc_service.py
tests/integration/test_dac_service.py
tests/integration/test_din_service.py
tests/integration/test_dout_service.py
tests/integration/test_error_handling.py
tests/integration/test_led_service.py
tests/integration/test_module.py
tests/integration/test_pwm_service.py
tests/integration/test_relay_service.py
tests/integration/test_tc_service.py
tests/unit/__init__.py
tests/unit/test_placeholder.py
edgepi_rpc_client-0.0.14.dist-info/LICENSE
edgepi_rpc_client-0.0.14.dist-info/METADATA
edgepi_rpc_client-0.0.14.dist-info/WHEEL
edgepi_rpc_client-0.0.14.dist-info/top_level.txt
edgepi_rpc_client-0.0.14.dist-info/RECORD
